headbot/__init__.py
headbot/client.py
headbot/settings.py
headbot-0.1.0.dist-info/LICENSE
headbot-0.1.0.dist-info/METADATA
headbot-0.1.0.dist-info/WHEEL
headbot-0.1.0.dist-info/top_level.txt
headbot-0.1.0.dist-info/RECORD
